MANIFEST.in
README.md
setup.py
eagle_automation/__init__.py
eagle_automation/config.py
eagle_automation/default.py
eagle_automation/diff.py
eagle_automation/drill.py
eagle_automation/export.py
eagle_automation/pea.py
eagle_automation.egg-info/PKG-INFO
eagle_automation.egg-info/SOURCES.txt
eagle_automation.egg-info/dependency_links.txt
eagle_automation.egg-info/entry_points.txt
eagle_automation.egg-info/pbr.json
eagle_automation.egg-info/requires.txt
eagle_automation.egg-info/top_level.txt