Metadata-Version: 1.1
Name: eagle-automation
Version: 0.1.9
Summary: Simple scripts supporting open hardware development using CadSoft EAGLE
Home-page: https://github.com/guyzmo/eagle-automation
Author: Tomaz Solc, Bernard Pratz
Author-email: tomaz.solc@tablix.org, guyzmo+pea@m0g.net
License: GPL
Platform: UNKNOWN
Classifier: Programming Language :: Python :: 3
Classifier: Programming Language :: Python :: 3.4
Classifier: Programming Language :: Python :: 2
Classifier: Programming Language :: Python :: 2.7
Classifier: Development Status :: 4 - Beta
Classifier: License :: OSI Approved
Classifier: Operating System :: Unix
